[
 {
  "allow_on_submit": 0, 
  "collapsible": 0, 
  "collapsible_depends_on": null, 
  "default": null, 
  "depends_on": null, 
  "description": null, 
  "docstatus": 0, 
  "doctype": "Custom Field", 
  "dt": "ToDo", 
  "fieldname": "book", 
  "fieldtype": "Link", 
  "hidden": 0, 
  "ignore_user_permissions": 0, 
  "ignore_xss_filter": 0, 
  "in_filter": 0, 
  "in_list_view": 0, 
  "in_standard_filter": 0, 
  "insert_after": "owner", 
  "label": "Book", 
  "modified": "2017-03-01 11:17:59.153889", 
  "name": "ToDo-book", 
  "no_copy": 0, 
  "options": "Book", 
  "permlevel": 0, 
  "precision": "", 
  "print_hide": 0, 
  "print_hide_if_no_value": 0, 
  "print_width": null, 
  "read_only": 0, 
  "report_hide": 0, 
  "reqd": 0, 
  "search_index": 0, 
  "unique": 0, 
  "width": null
 }, 
 {
  "allow_on_submit": 0, 
  "collapsible": 0, 
  "collapsible_depends_on": null, 
  "default": null, 
  "depends_on": null, 
  "description": null, 
  "docstatus": 0, 
  "doctype": "Custom Field", 
  "dt": "ToDo", 
  "fieldname": "publishing_date", 
  "fieldtype": "Date", 
  "hidden": 0, 
  "ignore_user_permissions": 0, 
  "ignore_xss_filter": 0, 
  "in_filter": 0, 
  "in_list_view": 0, 
  "in_standard_filter": 0, 
  "insert_after": "book", 
  "label": "Publishing Date", 
  "modified": "2017-03-01 11:19:36.358658", 
  "name": "ToDo-publishing_date", 
  "no_copy": 0, 
  "options": null, 
  "permlevel": 0, 
  "precision": "", 
  "print_hide": 0, 
  "print_hide_if_no_value": 0, 
  "print_width": null, 
  "read_only": 1, 
  "report_hide": 0, 
  "reqd": 0, 
  "search_index": 0, 
  "unique": 0, 
  "width": null
 }
]